ppm_reader/__init__.py
ppm_reader/__main__.py
micropython_ppm_reader-1.0.2.dist-info/LICENSE
micropython_ppm_reader-1.0.2.dist-info/METADATA
micropython_ppm_reader-1.0.2.dist-info/WHEEL
micropython_ppm_reader-1.0.2.dist-info/top_level.txt
micropython_ppm_reader-1.0.2.dist-info/RECORD
