Metadata-Version: 2.1
Name: micropython-ppm-reader
Version: 1.0.2
Summary: Decodes PPM signals from RC receivers
Author-email: redoxcode <redoxcode@github.com>
License: MIT License
Project-URL: Homepage, https://github.com/redoxcode/micropython-ppm_reader
Keywords: PPM,reader,rc,remote,receiver
Classifier: License :: OSI Approved :: MIT License
Classifier: Programming Language :: Python :: Implementation :: MicroPython
License-File: LICENSE
Provides-Extra: dev
